django_crontab/__init__.py
django_crontab/app_settings.py
django_crontab/crontab.py
django_crontab/models.py
django_crontab/management/__init__.py
django_crontab/management/commands/__init__.py
django_crontab/management/commands/crontab.py
dj_crontab-0.8.0.dist-info/LICENSE
dj_crontab-0.8.0.dist-info/METADATA
dj_crontab-0.8.0.dist-info/WHEEL
dj_crontab-0.8.0.dist-info/top_level.txt
dj_crontab-0.8.0.dist-info/RECORD
